{
  "project_info": {
    "project_number": "1098753954587",
    "project_id": "comffee-8c706",
    "storage_bucket": "comffee-8c706.appspot.com"
  },
  "client": [
    {
      "client_info": {
        "mobilesdk_app_id": "1:1098753954587:android:dc10908fd66f630c3639be",
        "android_client_info": {
          "package_name": "com.example.comffee"
        }
      },
      "oauth_client": [
        {
          "client_id": "1098753954587-1bot5sllpdd5g8oivde608oij70u1i01.apps.googleusercontent.com",
          "client_type": 3
        }
      ],
      "api_key": [
        {
          "current_key": "AIzaSyC9IvPQugLJ0Eek-08nuG_UaQdG_lwMiJQ"
        }
      ],
      "services": {
        "appinvite_service": {
          "other_platform_oauth_client": [
            {
              "client_id": "1098753954587-1bot5sllpdd5g8oivde608oij70u1i01.apps.googleusercontent.com",
              "client_type": 3
            }
          ]
        }
      }
    }
  ],
  "configuration_version": "1"
}